dev_observer/__init__.py
dev_observer/env_detection.py
dev_observer/log.py
dev_observer/settings.py
dev_observer/util.py
dev_observer/analysis/__init__.py
dev_observer/analysis/langgraph_provider.py
dev_observer/analysis/provider.py
dev_observer/analysis/stub.py
dev_observer/api/__init__.py
dev_observer/api/storage/__init__.py
dev_observer/api/storage/local_pb2.py
dev_observer/api/storage/local_pb2.pyi
dev_observer/api/storage/local_pb2_grpc.py
dev_observer/api/types/__init__.py
dev_observer/api/types/ai_pb2.py
dev_observer/api/types/ai_pb2.pyi
dev_observer/api/types/ai_pb2_grpc.py
dev_observer/api/types/config_pb2.py
dev_observer/api/types/config_pb2.pyi
dev_observer/api/types/config_pb2_grpc.py
dev_observer/api/types/observations_pb2.py
dev_observer/api/types/observations_pb2.pyi
dev_observer/api/types/observations_pb2_grpc.py
dev_observer/api/types/processing_pb2.py
dev_observer/api/types/processing_pb2.pyi
dev_observer/api/types/processing_pb2_grpc.py
dev_observer/api/types/repo_pb2.py
dev_observer/api/types/repo_pb2.pyi
dev_observer/api/types/repo_pb2_grpc.py
dev_observer/api/types/sites_pb2.py
dev_observer/api/types/sites_pb2.pyi
dev_observer/api/types/sites_pb2_grpc.py
dev_observer/api/web/__init__.py
dev_observer/api/web/config_pb2.py
dev_observer/api/web/config_pb2.pyi
dev_observer/api/web/config_pb2_grpc.py
dev_observer/api/web/observations_pb2.py
dev_observer/api/web/observations_pb2.pyi
dev_observer/api/web/observations_pb2_grpc.py
dev_observer/api/web/repositories_pb2.py
dev_observer/api/web/repositories_pb2.pyi
dev_observer/api/web/repositories_pb2_grpc.py
dev_observer/api/web/sites_pb2.py
dev_observer/api/web/sites_pb2.pyi
dev_observer/api/web/sites_pb2_grpc.py
dev_observer/flatten/__init__.py
dev_observer/flatten/flatten.py
dev_observer/observations/__init__.py
dev_observer/observations/local.py
dev_observer/observations/memory.py
dev_observer/observations/provider.py
dev_observer/observations/s3.py
dev_observer/processors/__init__.py
dev_observer-0.0.2.dist-info/METADATA
dev_observer-0.0.2.dist-info/WHEEL
dev_observer-0.0.2.dist-info/RECORD
